njcaa/__init__.py
njcaa/baseball/__init__.py
njcaa/baseball/baseball_pbp.py
njcaa/baseball/baseball_schedule.py
njcaa/baseball/baseball_stats.py
njcaa/baseball/baseball_teams.py
njcaa/baseball/baseball_utils.py
njcaa-0.0.1.dist-info/LICENSE
njcaa-0.0.1.dist-info/METADATA
njcaa-0.0.1.dist-info/WHEEL
njcaa-0.0.1.dist-info/top_level.txt
njcaa-0.0.1.dist-info/RECORD
